datareadingrequests.py
datareadingrequests-2.0.1.dist-info/LICENSE.md
datareadingrequests-2.0.1.dist-info/WHEEL
datareadingrequests-2.0.1.dist-info/METADATA
datareadingrequests-2.0.1.dist-info/RECORD
