Metadata-Version: 2.1
Name: datareadingrequests
Version: 2.0.1
Summary: A client for Energize Andover's Building Energy Gateway, with a focus on clarity and usability.
Home-page: https://github.com/tactlessfish/datareadingrequests
License: MIT
Author: fisher
Author-email: fisher521.fs@gmail.com
Requires-Python: >=3.8,<4.0
Classifier: License :: OSI Approved :: MIT License
Classifier: Programming Language :: Python :: 3
Classifier: Programming Language :: Python :: 3.10
Classifier: Programming Language :: Python :: 3.8
Classifier: Programming Language :: Python :: 3.9
Requires-Dist: requests (>=2.26.0,<3.0.0)
Project-URL: Repository, https://github.com/tactlessfish/datareadingrequests
